flask_gae_tests.py
setup.py
flask_gae_tests.egg-info/PKG-INFO
flask_gae_tests.egg-info/SOURCES.txt
flask_gae_tests.egg-info/dependency_links.txt
flask_gae_tests.egg-info/not-zip-safe
flask_gae_tests.egg-info/requires.txt
flask_gae_tests.egg-info/top_level.txt